vcf_consensus_builder/__init__.py
vcf_consensus_builder/cli.py
vcf_consensus_builder/io.py
vcf_consensus_builder/log.py
vcf_consensus_builder/vcf_consensus_builder.py
vcf_consensus_builder-0.1.0.dist-info/AUTHORS.rst
vcf_consensus_builder-0.1.0.dist-info/LICENSE
vcf_consensus_builder-0.1.0.dist-info/METADATA
vcf_consensus_builder-0.1.0.dist-info/WHEEL
vcf_consensus_builder-0.1.0.dist-info/entry_points.txt
vcf_consensus_builder-0.1.0.dist-info/top_level.txt
vcf_consensus_builder-0.1.0.dist-info/RECORD
