Metadata-Version: 2.1
Name: vcf-consensus-builder
Version: 0.1.0
Summary: Build a consensus sequence from a VCF and ref sequence masking low and no coverage positions.
Home-page: https://github.com/peterk87/vcf_consensus_builder
Author: Peter Kruczkiewicz
Author-email: peter.kruczkiewicz@gmail.com
License: MIT license
Keywords: vcf_consensus_builder
Platform: UNKNOWN
Classifier: Development Status :: 2 - Pre-Alpha
Classifier: Intended Audience :: Developers
Classifier: License :: OSI Approved :: MIT License
Classifier: Natural Language :: English
Classifier: Programming Language :: Python :: 3
Classifier: Programming Language :: Python :: 3.6
Classifier: Programming Language :: Python :: 3.7
Classifier: Programming Language :: Python :: 3.8
Requires-Python: >=3.5
Requires-Dist: Click (>=7.0)
Requires-Dist: attrs
Requires-Dist: pandas (>=0.25.0)
Requires-Dist: biopython (>=1.73)
Requires-Dist: numpy
